TradeWorld/__init__.py
TradeWorld/audio/__init__.py
TradeWorld/video/__init__.py
test/__init__.py
TradeWorld-2023.9.1.dist-info/LICENSE.txt
TradeWorld-2023.9.1.dist-info/METADATA
TradeWorld-2023.9.1.dist-info/WHEEL
TradeWorld-2023.9.1.dist-info/top_level.txt
TradeWorld-2023.9.1.dist-info/RECORD
